README.md
setup.py
dataframez/__init__.py
dataframez/catalog_writer.py
dataframez/read_from_catalog.py
dataframez.egg-info/PKG-INFO
dataframez.egg-info/SOURCES.txt
dataframez.egg-info/dependency_links.txt
dataframez.egg-info/top_level.txt
dataframez/catalogs/__init__.py
dataframez/catalogs/catalog.py
dataframez/catalogs/local.py
dataframez/data_interactors/__init__.py
dataframez/data_interactors/csv.py
dataframez/data_interactors/io.py
dataframez/data_interactors/parquet.py
dataframez/data_interactors/pickle.py
tests/__init__.py
tests/test_csv.py
tests/test_parquet.py
tests/test_pickle.py